seghouse/__init__.py
seghouse/__main__.py
seghouse/app.py
seghouse/config/__init__.py
seghouse/config/configuration.py
seghouse/config/data_type.py
seghouse/config/default_table_structure.py
seghouse/config/event_fields.py
seghouse/jobs/__init__.py
seghouse/jobs/send_to_warehouse.py
seghouse/logging.conf
seghouse/util/__init__.py
seghouse/util/aws_wrapper.py
seghouse/util/dataframe_util.py
seghouse/util/json_util.py
seghouse/warehouse/__init__.py
seghouse/warehouse/clickhouse.py
seghouse/warehouse/factory.py
seghouse/warehouse/warehouse.py
seghouse-0.18.0.dist-info/entry_points.txt
seghouse-0.18.0.dist-info/WHEEL
seghouse-0.18.0.dist-info/METADATA
seghouse-0.18.0.dist-info/RECORD
