Metadata-Version: 2.1
Name: seghouse
Version: 0.18.0
Summary: 
Author: Dinesh Sawant
Author-email: dineshsawant300@gmail.com
Requires-Python: >=3.7.1,<4.0.0
Classifier: Programming Language :: Python :: 3
Classifier: Programming Language :: Python :: 3.8
Classifier: Programming Language :: Python :: 3.9
Requires-Dist: PyYAML (>=5.3.1,<6.0.0)
Requires-Dist: click (>=7.1.2,<8.0.0)
Requires-Dist: clickhouse-driver[zstd,numpy,lz4] (>=0.2.0,<0.3.0)
Requires-Dist: pandas (>=1.2.0,<2.0.0)
Requires-Dist: pyhumps (>=1.6.1,<2.0.0)
Requires-Dist: tabulate (>=0.8.7,<0.9.0)
